{
  "blurb": "H",

  "centered": true,
  "next_level": "level1-15",

  "spawnx": 250,
  "spawny": 250,

  "tiles": [
    [{"template": "base_blue"},
    {"template": "base_white"},
    {"template": "base_blue"},
    {"template": "base_white"},
    {"template": "base_blue"},
    {"template": "base_white"},
    {"template": "base_blue"},
    {"template": "base_white"},
    {"template": "base_blue"},
    {"template": "base_white"}],

    [{"template": "base_white"},
    {"template": "base_blue"},
    {"template": "base_white"},
    {"template": "base_blue"},
    {"template": "base_white"},
    {"template": "base_blue"},
    {"template": "base_white"},
    {"template": "base_blue"},
    {"template": "base_white"},
    {"template": "base_blue"}],

    [{"template": "base_blue"},
    {"template": "base_white"},
    {"template": "base_blue"},
    {"template": "base_white"},
    {"template": "base_blue"},
    {"template": "base_white"},
    {"template": "base_blue"},
    {"template": "base_white"},
    {"template": "base_blue"},
    {"template": "base_white"}],

    [{"template": "base_white"},
    {"template": "base_blue"},
    {"template": "base_white"},
    {"template": "base_blue"},
    {"template": "base_white"},
    {"template": "base_blue"},
    {"template": "base_white"},
    {"template": "base_blue"},
    {"template": "base_white"},
    {"template": "base_blue"}],

    [{"template": "base_blue"},
    {"template": "base_white"},
    {"template": "base_blue"},
    {"template": "base_white"},
    {"template": "end_zone", "newx": 250, "newy": 250},
    {"template": "end_zone", "newx": 250, "newy": 250},
    {"template": "base_blue"},
    {"template": "base_white"},
    {"template": "base_blue"},
    {"template": "base_white"}],

    [{"template": "base_white"},
    {"template": "base_blue"},
    {"template": "base_white"},
    {"template": "base_blue"},
    {"template": "end_zone", "newx": 250, "newy": 250},
    {"template": "end_zone", "newx": 250, "newy": 250},
    {"template": "base_white"},
    {"template": "base_blue"},
    {"template": "base_white"},
    {"template": "base_blue"}],

    [{"template": "base_blue"},
    {"template": "base_white"},
    {"template": "base_blue"},
    {"template": "base_white"},
    {"template": "base_blue"},
    {"template": "base_white"},
    {"template": "base_blue"},
    {"template": "base_white"},
    {"template": "base_blue"},
    {"template": "base_white"}],

    [{"template": "base_white"},
    {"template": "base_blue"},
    {"template": "base_white"},
    {"template": "base_blue"},
    {"template": "base_white"},
    {"template": "base_blue"},
    {"template": "base_white"},
    {"template": "base_blue"},
    {"template": "base_white"},
    {"template": "base_blue"}],

    [{"template": "base_blue"},
    {"template": "base_white"},
    {"template": "base_blue"},
    {"template": "base_white"},
    {"template": "base_blue"},
    {"template": "base_white"},
    {"template": "base_blue"},
    {"template": "base_white"},
    {"template": "base_blue"},
    {"template": "base_white"}],

    [{"template": "base_white"},
    {"template": "base_blue"},
    {"template": "base_white"},
    {"template": "base_blue"},
    {"template": "base_white"},
    {"template": "base_blue"},
    {"template": "base_white"},
    {"template": "base_blue"},
    {"template": "base_white"},
    {"template": "base_blue"}]
  ],

  "walls": [
    {"sx": 0, "sy": 0, "ex": 500, "ey": 0},
    {"sx": 500, "sy": 0, "ex": 500, "ey": 500},
    {"sx": 0, "sy": 0, "ex": 0, "ey": 500},
    {"sx": 0, "sy": 500, "ex": 500, "ey": 500}
  ],
  "enemies": [
    {"x": 175, "y": 175, "speed": 3, "path": [[175, 175], [325, 175], [325, 325], [175, 325]]},
    {"x": 375, "y": 125, "speed": 4, "path": [[375, 125], [375, 375], [125, 375], [125, 125]]},
    {"x": 75, "y": 425, "speed": 6, "path": [[75, 425],  [425, 425], [425, 75], [75, 75]]},
    {"x": 475, "y": 475, "speed": 8, "path": [[475, 475], [25, 475], [25, 25], [475, 25]]}
  ],
  "coins": [
    {"x": 75, "y": 75},
    {"x": 75, "y": 250},
    {"x": 75, "y": 425},
    {"x": 250, "y": 75},
    {"x": 250, "y": 425},
    {"x": 425, "y": 75},
    {"x": 425, "y": 250},
    {"x": 425, "y": 425}
  ]
}